LICENSE.txt
README.md
setup.cfg
setup.py
joulescope_server/__init__.py
joulescope_server/__main__.py
joulescope_server/client.py
joulescope_server/framer.py
joulescope_server/server.py
joulescope_server/version.py
joulescope_server.egg-info/PKG-INFO
joulescope_server.egg-info/SOURCES.txt
joulescope_server.egg-info/dependency_links.txt
joulescope_server.egg-info/entry_points.txt
joulescope_server.egg-info/requires.txt
joulescope_server.egg-info/top_level.txt
joulescope_server/test/__init__.py
joulescope_server/test/test_framer.py