Metadata-Version: 2.1
Name: joulescope-server
Version: 0.1.0
Summary: Joulescope™ server
Home-page: https://joulescope.readthedocs.io
Author: Jetperch LLC
Author-email: joulescope-dev@jetperch.com
License: Apache 2.0
Project-URL: Bug Reports, https://github.com/jetperch/pyjoulescope_server/issues
Project-URL: Funding, https://www.joulescope.com
Project-URL: Twitter, https://twitter.com/joulescope
Project-URL: Source, https://github.com/jetperch/pyjoulescope_server/
Keywords: joulescope server
Platform: UNKNOWN
Classifier: Development Status :: 2 - Pre-Alpha
Classifier: Intended Audience :: End Users/Desktop
Classifier: Topic :: Scientific/Engineering
Classifier: Topic :: Software Development :: Embedded Systems
Classifier: License :: OSI Approved :: Apache Software License
Classifier: Programming Language :: Python :: 3.6
Classifier: Programming Language :: Python :: 3.7
Classifier: Programming Language :: Python :: 3.8
Requires-Python: ~=3.6
Provides-Extra: dev
